tess_bite/__init__.py
tess_bite/bite.py
tess_bite/core.py
tess_bite-0.1.0.dist-info/LICENSE
tess_bite-0.1.0.dist-info/WHEEL
tess_bite-0.1.0.dist-info/METADATA
tess_bite-0.1.0.dist-info/RECORD
