Metadata-Version: 2.1
Name: tess-bite
Version: 0.1.0
Summary: Take a bite out of TESS Full Frame Images using HTTP range requests.
Home-page: https://github.com/SSDataLab/tess-bite
License: MIT
Keywords: NASA, TESS, Astronomy
Author: Geert Barentsen
Author-email: hello@geert.io
Requires-Python: >=3.7,<4.0
Classifier: Intended Audience :: Science/Research
Classifier: License :: OSI Approved :: MIT License
Classifier: Programming Language :: Python :: 3
Classifier: Programming Language :: Python :: 3.7
Classifier: Programming Language :: Python :: 3.8
Classifier: Programming Language :: Python :: 3.9
Classifier: Topic :: Scientific/Engineering :: Astronomy
Requires-Dist: astropy (>=4.0)
Requires-Dist: httpx (>=0.16.1)
Requires-Dist: lightkurve (>=1.11.3,<2.0.0)
Requires-Dist: numpy (>=1.19)
Requires-Dist: tess-locator (>=0.2.0,<0.3.0)
Project-URL: Repository, https://github.com/SSDataLab/tess-bite
